{
  "device": "xcvu9p-flga2104-2L",
  "package": "FCCGA1156",
  "speed_grade": "-2",
  "temperature": "commercial",
  "comment": "Xilinx Virtex UltraScale+ (VU9P) device model extracted from PG252 and DS922",

  "inventory": {
    "clbs": {
      "count": 182400,
      "comment": "Configurable Logic Blocks; each contains 8 LUTs + 16 FFs"
    },
    "luts": {
      "count": 1457600,
      "type": "LUT6",
      "comment": "6-input lookup tables (can also be used as 2×5-input, SRAM, SRL)"
    },
    "bram36": {
      "count": 2160,
      "capacity_bits": 36864,
      "comment": "36 Kb blocks (can be split as BRAM18)"
    },
    "dsp48e2": {
      "count": 6840,
      "comment": "48-bit arithmetic slices (multiply, add, accumulate)"
    },
    "gty": {
      "count": 32,
      "max_speed_gbps": 32.75,
      "comment": "High-speed transceivers"
    },
    "cmt": {
      "count": 6,
      "comment": "Clock Management Tiles (MMCM + PLL)"
    }
  },

  "dff_nodes": [
    {
      "name": "CLB_DFFE",
      "type": "CLB_FF",
      "count": 1459200,
      "source": "ROUTING",
      "comment": "CLB flip-flops driven by routing (programmable interconnect)"
    },
    {
      "name": "CLB_DFFE",
      "type": "CLB_FF",
      "count": 729600,
      "source": "CARRY",
      "comment": "CLB flip-flops driven by carry chain outputs"
    },
    {
      "name": "CLB_DFFE",
      "type": "CLB_FF",
      "count": 729600,
      "source": "LUT",
      "comment": "CLB flip-flops driven by LUT outputs"
    },
    {
      "name": "BRAM_READ",
      "type": "BRAM_READ_OUTPUT",
      "count": 77760,
      "comment": "BRAM36 read port registered outputs (2,160 blocks × 36 bits)"
    },
    {
      "name": "DSP_ACCUMULATOR",
      "type": "DSP_ACCUMULATOR_FF",
      "count": 328320,
      "comment": "DSP48E2 accumulator registers (6,840 blocks × 48 bits)"
    },
    {
      "name": "GTY_RX_DATA",
      "type": "GTY_RX_DATA_FF",
      "count": 2048,
      "comment": "GTY transceiver RX data latches (32 lanes × 64 bits)"
    }
  ],

  "comb_nodes": [
    {
      "name": "LUT6",
      "type": "LUT6",
      "inputs": 6,
      "outputs": 1,
      "count": 1457600,
      "comment": "6-input lookup tables"
    },
    {
      "name": "CARRY_CHAIN",
      "type": "CARRY_FA",
      "inputs": 3,
      "outputs": 2,
      "count": 182400,
      "comment": "Ripple-carry full-adder chains (one per CLB column)"
    },
    {
      "name": "MUXF7",
      "type": "MUXF7",
      "inputs": 2,
      "outputs": 1,
      "count": 728000,
      "comment": "2-to-1 wide multiplexers (CLB inter-slice)"
    },
    {
      "name": "MUXF8",
      "type": "MUXF8",
      "inputs": 2,
      "outputs": 1,
      "count": 364000,
      "comment": "2-to-1 wide multiplexers (CLB pair)"
    },
    {
      "name": "ROUTING_SWITCH",
      "type": "ROUTING_SWITCH",
      "inputs": 20,
      "outputs": 4,
      "count": 250,
      "comment": "Programmable interconnect (routing switch matrices)"
    },
    {
      "name": "DSP_MULTIPLY",
      "type": "DSP_MULTIPLY",
      "inputs": 48,
      "outputs": 48,
      "count": 6840,
      "comment": "DSP48E2 multiply units (25×18)"
    },
    {
      "name": "DSP_ADDSUB",
      "type": "DSP_ADDSUB",
      "inputs": 96,
      "outputs": 48,
      "count": 6840,
      "comment": "DSP48E2 add/subtract units"
    }
  ],

  "connections": [
    {
      "from": "LUT6",
      "to": "CLB_DFFE",
      "type": "data",
      "comment": "LUT outputs drive CLB flip-flops"
    },
    {
      "from": "CARRY_CHAIN",
      "to": "CLB_DFFE",
      "type": "data",
      "comment": "Carry chain outputs drive CLB flip-flops"
    },
    {
      "from": "MUXF7",
      "to": "CLB_DFFE",
      "type": "data",
      "comment": "MUXF7 outputs drive CLB flip-flops (inter-slice)"
    },
    {
      "from": "ROUTING_SWITCH",
      "to": "LUT6",
      "type": "routing",
      "comment": "Programmable interconnect drives LUT inputs"
    },
    {
      "from": "DSP_MULTIPLY",
      "to": "DSP_ACCUMULATOR",
      "type": "data",
      "comment": "DSP multiply product feeds DSP accumulator"
    },
    {
      "from": "DSP_ADDSUB",
      "to": "DSP_ACCUMULATOR",
      "type": "data",
      "comment": "DSP add/subtract result feeds DSP accumulator"
    }
  ]
}
