{
  "device": "fpga_blank",
  "kind": "fpga_blank",
  "part_ref": "Xilinx Virtex UltraScale+ VU9P (XILINX_VU9P_SPEC_EXTRACTION.md)",
  "comment": "GENERATED by gen_fpga_blank.py from device_profiles/vu9p.yaml \u2014 DO NOT EDIT BY HAND. THE one identical FPGA blank: the internally-connected fabric reference (full real part, undifferentiated). A BLANK ASSIGNS NOTHING: no clock tables, no module names, no placements, no addresses \u2014 clocks arrive with the oscillator modules at install (phase 4); boards are identical instances named at addressing (phase 3).",
  "fabric": {
    "registers": 262144,
    "word_bits": 64
  },
  "address_space_geometry": {
    "size": 268435456,
    "slot_alignment": 4096,
    "cdc_region_size": 1048576
  },
  "io_geometry": {
    "gty_lanes": 32,
    "io_banks": 44
  },
  "resource_budget": {
    "clb": {
      "capacity": 182400,
      "unit": "slice"
    },
    "bram": {
      "capacity": 2160,
      "unit": "block36"
    },
    "dsp": {
      "capacity": 6840,
      "unit": "dsp48e2"
    }
  }
}
